{
  "gridstate": "array/gridstate.json",
  "seed": 0,
  "steps": 140,
  "rows": [
    {
      "t": 0,
      "n_cell": 513,
      "n_total": 4000,
      "n_match": 4000,
      "n_mismatch": 0,
      "n_cell_outside_morph": 0,
      "n_morph_without_cell": 0,
      "mean_match": 1.0,
      "morphological_health": 1.0,
      "atp_mean": 48708.87329434698,
      "atp_min": 373.0,
      "atp_max": 99849.0,
      "frac_atp_lt1": 0.0,
      "glucose_mean": 75.97465886939571,
      "glucose_min": 50.0,
      "damage_mean": 0.4851558630656066,
      "damage_max": 0.9998384714126587,
      "atp_generated_mean": 75.97465886939571,
      "atp_generated_max": 100.0
    },
    {
      "t": 1,
      "n_cell": 576,
      "n_total": 4000,
      "n_match": 3937,
      "n_mismatch": 63,
      "n_cell_outside_morph": 63,
      "n_morph_without_cell": 0,
      "mean_match": 0.98425,
      "morphological_health": 0.7279615972800295,
      "atp_mean": 20638.81076388889,
      "atp_min": 65.0,
      "atp_max": 88438.0,
      "frac_atp_lt1": 0.0,
      "glucose_mean": 60.87847222222222,
      "glucose_min": 22.0,
      "damage_mean": 0.01928158404512538,
      "damage_max": 0.4995136857032776,
      "atp_generated_mean": 60.87847222222222,
      "atp_generated_max": 90.0
    },
    {
      "t": 2,
      "n_cell": 595,
      "n_total": 4000,
      "n_match": 3918,
      "n_mismatch": 82,
      "n_cell_outside_morph": 82,
      "n_morph_without_cell": 0,
      "mean_match": 0.9795,
      "morphological_health": 0.6608285635813778,
      "atp_mean": 11950.678991596638,
      "atp_min": 27.0,
      "atp_max": 49307.0,
      "frac_atp_lt1": 0.0,
      "glucose_mean": 53.005042016806726,
      "glucose_min": 20.0,
      "damage_mean": 0.0,
      "damage_max": 0.0,
      "atp_generated_mean": 53.005042016806726,
      "atp_generated_max": 81.0
    },
    {
      "t": 3,
      "n_cell": 595,
      "n_total": 4000,
      "n_match": 3918,
      "n_mismatch": 82,
      "n_cell_outside_morph": 82,
      "n_morph_without_cell": 0,
      "mean_match": 0.9795,
      "morphological_health": 0.6608285635813778,
      "atp_mean": 7855.231932773109,
      "atp_min": 14.0,
      "atp_max": 39486.0,
      "frac_atp_lt1": 0.0,
      "glucose_mean": 47.707563025210085,
      "glucose_min": 18.0,
      "damage_mean": 0.0,
      "damage_max": 0.0,
      "atp_generated_mean": 47.707563025210085,
      "atp_generated_max": 73.0
    },
    {
      "t": 4,
      "n_cell": 595,
      "n_total": 4000,
      "n_match": 3918,
      "n_mismatch": 82,
      "n_cell_outside_morph": 82,
      "n_morph_without_cell": 0,
      "mean_match": 0.9795,
      "morphological_health": 0.6608285635813778,
      "atp_mean": 4835.394957983193,
      "atp_min": 9.0,
      "atp_max": 30414.0,
      "frac_atp_lt1": 0.0,
      "glucose_mean": 42.92773109243697,
      "glucose_min": 16.0,
      "damage_mean": 0.0,
      "damage_max": 0.0,
      "atp_generated_mean": 42.92773109243697,
      "atp_generated_max": 66.0
    },
    {
      "t": 5,
      "n_cell": 595,
      "n_total": 4000,
      "n_match": 3918,
      "n_mismatch": 82,
      "n_cell_outside_morph": 82,
      "n_morph_without_cell": 0,
      "mean_match": 0.9795,
      "morphological_health": 0.6608285635813778,
      "atp_mean": 2794.5899159663863,
      "atp_min": 5.0,
      "atp_max": 21909.0,
      "frac_atp_lt1": 0.0,
      "glucose_mean": 38.628571428571426,
      "glucose_min": 14.0,
      "damage_mean": 0.0,
      "damage_max": 0.0,
      "atp_generated_mean": 38.628571428571426,
      "atp_generated_max": 59.0
    },
    {
      "t": 6,
      "n_cell": 595,
      "n_total": 4000,
      "n_match": 3918,
      "n_mismatch": 82,
      "n_cell_outside_morph": 82,
      "n_morph_without_cell": 0,
      "mean_match": 0.9795,
      "morphological_health": 0.6608285635813778,
      "atp_mean": 1508.5142857142857,
      "atp_min": 4.0,
      "atp_max": 14643.0,
      "frac_atp_lt1": 0.0,
      "glucose_mean": 34.732773109243695,
      "glucose_min": 13.0,
      "damage_mean": 0.0,
      "damage_max": 0.0,
      "atp_generated_mean": 34.732773109243695,
      "atp_generated_max": 53.0
    },
    {
      "t": 7,
      "n_cell": 595,
      "n_total": 4000,
      "n_match": 3918,
      "n_mismatch": 82,
      "n_cell_outside_morph": 82,
      "n_morph_without_cell": 0,
      "mean_match": 0.9795,
      "morphological_health": 0.6608285635813778,
      "atp_mean": 755.7579831932773,
      "atp_min": 4.0,
      "atp_max": 9466.0,
      "frac_atp_lt1": 0.0,
      "glucose_mean": 31.223529411764705,
      "glucose_min": 12.0,
      "damage_mean": 0.0,
      "damage_max": 0.0,
      "atp_generated_mean": 31.223529411764705,
      "atp_generated_max": 48.0
    },
    {
      "t": 8,
      "n_cell": 595,
      "n_total": 4000,
      "n_match": 3918,
      "n_mismatch": 82,
      "n_cell_outside_morph": 82,
      "n_morph_without_cell": 0,
      "mean_match": 0.9795,
      "morphological_health": 0.6608285635813778,
      "atp_mean": 347.2840336134454,
      "atp_min": 4.0,
      "atp_max": 5796.0,
      "frac_atp_lt1": 0.0,
      "glucose_mean": 28.057142857142857,
      "glucose_min": 11.0,
      "damage_mean": 0.0,
      "damage_max": 0.0,
      "atp_generated_mean": 28.057142857142857,
      "atp_generated_max": 43.0
    },
    {
      "t": 9,
      "n_cell": 595,
      "n_total": 4000,
      "n_match": 3918,
      "n_mismatch": 82,
      "n_cell_outside_morph": 82,
      "n_morph_without_cell": 0,
      "mean_match": 0.9795,
      "morphological_health": 0.6608285635813778,
      "atp_mean": 144.02857142857144,
      "atp_min": 4.0,
      "atp_max": 3196.0,
      "frac_atp_lt1": 0.0,
      "glucose_mean": 25.24705882352941,
      "glucose_min": 10.0,
      "damage_mean": 0.0,
      "damage_max": 0.0,
      "atp_generated_mean": 25.24705882352941,
      "atp_generated_max": 39.0
    },
    {
      "t": 10,
      "n_cell": 595,
      "n_total": 4000,
      "n_match": 3918,
      "n_mismatch": 82,
      "n_cell_outside_morph": 82,
      "n_morph_without_cell": 0,
      "mean_match": 0.9795,
      "morphological_health": 0.6608285635813778,
      "atp_mean": 56.44873949579832,
      "atp_min": 4.0,
      "atp_max": 1361.0,
      "frac_atp_lt1": 0.0,
      "glucose_mean": 22.71764705882353,
      "glucose_min": 9.0,
      "damage_mean": 0.0,
      "damage_max": 0.0,
      "atp_generated_mean": 22.71764705882353,
      "atp_generated_max": 35.0
    },
    {
      "t": 11,
      "n_cell": 595,
      "n_total": 4000,
      "n_match": 3918,
      "n_mismatch": 82,
      "n_cell_outside_morph": 82,
      "n_morph_without_cell": 0,
      "mean_match": 0.9795,
      "morphological_health": 0.6608285635813778,
      "atp_mean": 22.96638655462185,
      "atp_min": 4.0,
      "atp_max": 514.0,
      "frac_atp_lt1": 0.0,
      "glucose_mean": 20.46890756302521,
      "glucose_min": 8.0,
      "damage_mean": 0.0,
      "damage_max": 0.0,
      "atp_generated_mean": 20.46890756302521,
      "atp_generated_max": 32.0
    },
    {
      "t": 12,
      "n_cell": 595,
      "n_total": 4000,
      "n_match": 3918,
      "n_mismatch": 82,
      "n_cell_outside_morph": 82,
      "n_morph_without_cell": 0,
      "mean_match": 0.9795,
      "morphological_health": 0.6608285635813778,
      "atp_mean": 10.583193277310924,
      "atp_min": 4.0,
      "atp_max": 195.0,
      "frac_atp_lt1": 0.0,
      "glucose_mean": 18.438655462184872,
      "glucose_min": 7.0,
      "damage_mean": 0.0,
      "damage_max": 0.0,
      "atp_generated_mean": 18.438655462184872,
      "atp_generated_max": 29.0
    },
    {
      "t": 13,
      "n_cell": 595,
      "n_total": 4000,
      "n_match": 3918,
      "n_mismatch": 82,
      "n_cell_outside_morph": 82,
      "n_morph_without_cell": 0,
      "mean_match": 0.9795,
      "morphological_health": 0.6608285635813778,
      "atp_mean": 6.144537815126051,
      "atp_min": 4.0,
      "atp_max": 73.0,
      "frac_atp_lt1": 0.0,
      "glucose_mean": 16.625210084033615,
      "glucose_min": 6.0,
      "damage_mean": 0.0,
      "damage_max": 0.0,
      "atp_generated_mean": 16.625210084033615,
      "atp_generated_max": 26.0
    },
    {
      "t": 14,
      "n_cell": 595,
      "n_total": 4000,
      "n_match": 3918,
      "n_mismatch": 82,
      "n_cell_outside_morph": 82,
      "n_morph_without_cell": 0,
      "mean_match": 0.9795,
      "morphological_health": 0.6608285635813778,
      "atp_mean": 4.568067226890756,
      "atp_min": 4.0,
      "atp_max": 28.0,
      "frac_atp_lt1": 0.0,
      "glucose_mean": 15.026890756302521,
      "glucose_min": 5.0,
      "damage_mean": 0.0,
      "damage_max": 0.0,
      "atp_generated_mean": 15.026890756302521,
      "atp_generated_max": 23.0
    },
    {
      "t": 15,
      "n_cell": 595,
      "n_total": 4000,
      "n_match": 3918,
      "n_mismatch": 82,
      "n_cell_outside_morph": 82,
      "n_morph_without_cell": 0,
      "mean_match": 0.9795,
      "morphological_health": 0.6608285635813778,
      "atp_mean": 4.13109243697479,
      "atp_min": 4.0,
      "atp_max": 13.0,
      "frac_atp_lt1": 0.0,
      "glucose_mean": 13.576470588235294,
      "glucose_min": 4.0,
      "damage_mean": 0.0,
      "damage_max": 0.0,
      "atp_generated_mean": 13.576470588235294,
      "atp_generated_max": 21.0
    },
    {
      "t": 16,
      "n_cell": 595,
      "n_total": 4000,
      "n_match": 3918,
      "n_mismatch": 82,
      "n_cell_outside_morph": 82,
      "n_morph_without_cell": 0,
      "mean_match": 0.9795,
      "morphological_health": 0.6608285635813778,
      "atp_mean": 4.005042016806723,
      "atp_min": 4.0,
      "atp_max": 6.0,
      "frac_atp_lt1": 0.0,
      "glucose_mean": 12.24033613445378,
      "glucose_min": 3.0,
      "damage_mean": 0.0,
      "damage_max": 0.0,
      "atp_generated_mean": 12.24033613445378,
      "atp_generated_max": 19.0
    },
    {
      "t": 17,
      "n_cell": 595,
      "n_total": 4000,
      "n_match": 3918,
      "n_mismatch": 82,
      "n_cell_outside_morph": 82,
      "n_morph_without_cell": 0,
      "mean_match": 0.9795,
      "morphological_health": 0.6608285635813778,
      "atp_mean": 4.0,
      "atp_min": 4.0,
      "atp_max": 4.0,
      "frac_atp_lt1": 0.0,
      "glucose_mean": 11.043697478991596,
      "glucose_min": 2.0,
      "damage_mean": 0.0,
      "damage_max": 0.0,
      "atp_generated_mean": 11.043697478991596,
      "atp_generated_max": 17.0
    },
    {
      "t": 18,
      "n_cell": 595,
      "n_total": 4000,
      "n_match": 3918,
      "n_mismatch": 82,
      "n_cell_outside_morph": 82,
      "n_morph_without_cell": 0,
      "mean_match": 0.9795,
      "morphological_health": 0.6608285635813778,
      "atp_mean": 4.0,
      "atp_min": 4.0,
      "atp_max": 4.0,
      "frac_atp_lt1": 0.0,
      "glucose_mean": 9.98655462184874,
      "glucose_min": 1.0,
      "damage_mean": 0.0,
      "damage_max": 0.0,
      "atp_generated_mean": 9.98655462184874,
      "atp_generated_max": 15.0
    },
    {
      "t": 19,
      "n_cell": 595,
      "n_total": 4000,
      "n_match": 3918,
      "n_mismatch": 82,
      "n_cell_outside_morph": 82,
      "n_morph_without_cell": 0,
      "mean_match": 0.9795,
      "morphological_health": 0.6608285635813778,
      "atp_mean": 4.0,
      "atp_min": 4.0,
      "atp_max": 4.0,
      "frac_atp_lt1": 0.0,
      "glucose_mean": 8.98655462184874,
      "glucose_min": 0.0,
      "damage_mean": 0.0,
      "damage_max": 0.0,
      "atp_generated_mean": 8.98655462184874,
      "atp_generated_max": 14.0
    },
    {
      "t": 20,
      "n_cell": 595,
      "n_total": 4000,
      "n_match": 3918,
      "n_mismatch": 82,
      "n_cell_outside_morph": 82,
      "n_morph_without_cell": 0,
      "mean_match": 0.9795,
      "morphological_health": 0.6608285635813778,
      "atp_mean": 3.9899159663865547,
      "atp_min": 3.0,
      "atp_max": 4.0,
      "frac_atp_lt1": 0.0,
      "glucose_mean": 7.996638655462185,
      "glucose_min": 0.0,
      "damage_mean": 0.0,
      "damage_max": 0.0,
      "atp_generated_mean": 7.996638655462185,
      "atp_generated_max": 13.0
    },
    {
      "t": 21,
      "n_cell": 595,
      "n_total": 4000,
      "n_match": 3918,
      "n_mismatch": 82,
      "n_cell_outside_morph": 82,
      "n_morph_without_cell": 0,
      "mean_match": 0.9795,
      "morphological_health": 0.6608285635813778,
      "atp_mean": 3.9630252100840337,
      "atp_min": 2.0,
      "atp_max": 4.0,
      "frac_atp_lt1": 0.0,
      "glucose_mean": 7.023529411764706,
      "glucose_min": 0.0,
      "damage_mean": 0.0,
      "damage_max": 0.0,
      "atp_generated_mean": 7.023529411764706,
      "atp_generated_max": 12.0
    },
    {
      "t": 22,
      "n_cell": 595,
      "n_total": 4000,
      "n_match": 3918,
      "n_mismatch": 82,
      "n_cell_outside_morph": 82,
      "n_morph_without_cell": 0,
      "mean_match": 0.9795,
      "morphological_health": 0.6608285635813778,
      "atp_mean": 3.919327731092437,
      "atp_min": 1.0,
      "atp_max": 4.0,
      "frac_atp_lt1": 0.0,
      "glucose_mean": 6.067226890756302,
      "glucose_min": 0.0,
      "damage_mean": 0.0,
      "damage_max": 0.0,
      "atp_generated_mean": 6.067226890756302,
      "atp_generated_max": 11.0
    },
    {
      "t": 23,
      "n_cell": 589,
      "n_total": 4000,
      "n_match": 3922,
      "n_mismatch": 78,
      "n_cell_outside_morph": 77,
      "n_morph_without_cell": 1,
      "mean_match": 0.9805,
      "morphological_health": 0.6744534182235946,
      "atp_mean": 3.8828522920203734,
      "atp_min": 1.0,
      "atp_max": 4.0,
      "frac_atp_lt1": 0.0,
      "glucose_mean": 5.195246179966044,
      "glucose_min": 0.0,
      "damage_mean": 0.0,
      "damage_max": 0.0,
      "atp_generated_mean": 5.195246179966044,
      "atp_generated_max": 10.0
    },
    {
      "t": 24,
      "n_cell": 579,
      "n_total": 4000,
      "n_match": 3920,
      "n_mismatch": 80,
      "n_cell_outside_morph": 73,
      "n_morph_without_cell": 7,
      "mean_match": 0.98,
      "morphological_health": 0.6676079717550942,
      "atp_mean": 3.844559585492228,
      "atp_min": 1.0,
      "atp_max": 4.0,
      "frac_atp_lt1": 0.0,
      "glucose_mean": 4.373056994818653,
      "glucose_min": 0.0,
      "damage_mean": 0.0,
      "damage_max": 0.0,
      "atp_generated_mean": 4.373056994818653,
      "atp_generated_max": 9.0
    },
    {
      "t": 25,
      "n_cell": 569,
      "n_total": 4000,
      "n_match": 3918,
      "n_mismatch": 82,
      "n_cell_outside_morph": 69,
      "n_morph_without_cell": 13,
      "mean_match": 0.9795,
      "morphological_health": 0.6608285635813778,
      "atp_mean": 3.759226713532513,
      "atp_min": 1.0,
      "atp_max": 4.0,
      "frac_atp_lt1": 0.0,
      "glucose_mean": 3.585237258347979,
      "glucose_min": 0.0,
      "damage_mean": 0.0,
      "damage_max": 0.0,
      "atp_generated_mean": 3.585237258347979,
      "atp_generated_max": 8.0
    },
    {
      "t": 26,
      "n_cell": 550,
      "n_total": 4000,
      "n_match": 3921,
      "n_mismatch": 79,
      "n_cell_outside_morph": 58,
      "n_morph_without_cell": 21,
      "mean_match": 0.98025,
      "morphological_health": 0.6710224022568508,
      "atp_mean": 3.6872727272727275,
      "atp_min": 1.0,
      "atp_max": 4.0,
      "frac_atp_lt1": 0.0,
      "glucose_mean": 2.8763636363636365,
      "glucose_min": 0.0,
      "damage_mean": 0.0,
      "damage_max": 0.0,
      "atp_generated_mean": 2.8763636363636365,
      "atp_generated_max": 7.0
    },
    {
      "t": 27,
      "n_cell": 528,
      "n_total": 4000,
      "n_match": 3919,
      "n_mismatch": 81,
      "n_cell_outside_morph": 48,
      "n_morph_without_cell": 33,
      "mean_match": 0.97975,
      "morphological_health": 0.6642100507448424,
      "atp_mean": 3.5757575757575757,
      "atp_min": 1.0,
      "atp_max": 4.0,
      "frac_atp_lt1": 0.0,
      "glucose_mean": 2.2196969696969697,
      "glucose_min": 0.0,
      "damage_mean": 0.0,
      "damage_max": 0.0,
      "atp_generated_mean": 2.2196969696969697,
      "atp_generated_max": 6.0
    },
    {
      "t": 28,
      "n_cell": 492,
      "n_total": 4000,
      "n_match": 3921,
      "n_mismatch": 79,
      "n_cell_outside_morph": 29,
      "n_morph_without_cell": 50,
      "mean_match": 0.98025,
      "morphological_health": 0.6710224022568508,
      "atp_mean": 3.4878048780487805,
      "atp_min": 1.0,
      "atp_max": 4.0,
      "frac_atp_lt1": 0.0,
      "glucose_mean": 1.6585365853658536,
      "glucose_min": 0.0,
      "damage_mean": 0.0,
      "damage_max": 0.0,
      "atp_generated_mean": 1.6585365853658536,
      "atp_generated_max": 5.0
    },
    {
      "t": 29,
      "n_cell": 458,
      "n_total": 4000,
      "n_match": 3923,
      "n_mismatch": 77,
      "n_cell_outside_morph": 11,
      "n_morph_without_cell": 66,
      "mean_match": 0.98075,
      "morphological_health": 0.6779010959589112,
      "atp_mean": 3.3275109170305677,
      "atp_min": 1.0,
      "atp_max": 4.0,
      "frac_atp_lt1": 0.0,
      "glucose_mean": 1.1266375545851528,
      "glucose_min": 0.0,
      "damage_mean": 0.0,
      "damage_max": 0.0,
      "atp_generated_mean": 1.1266375545851528,
      "atp_generated_max": 4.0
    },
    {
      "t": 30,
      "n_cell": 410,
      "n_total": 4000,
      "n_match": 3897,
      "n_mismatch": 103,
      "n_cell_outside_morph": 0,
      "n_morph_without_cell": 103,
      "mean_match": 0.97425,
      "morphological_health": 0.5934830081400398,
      "atp_mean": 3.202439024390244,
      "atp_min": 1.0,
      "atp_max": 4.0,
      "frac_atp_lt1": 0.0,
      "glucose_mean": 0.6560975609756098,
      "glucose_min": 0.0,
      "damage_mean": 0.0,
      "damage_max": 0.0,
      "atp_generated_mean": 0.6560975609756098,
      "atp_generated_max": 3.0
    },
    {
      "t": 31,
      "n_cell": 356,
      "n_total": 4000,
      "n_match": 3843,
      "n_mismatch": 157,
      "n_cell_outside_morph": 0,
      "n_morph_without_cell": 157,
      "mean_match": 0.96075,
      "morphological_health": 0.4489602205850416,
      "atp_mean": 3.033707865168539,
      "atp_min": 1.0,
      "atp_max": 4.0,
      "frac_atp_lt1": 0.0,
      "glucose_mean": 0.25842696629213485,
      "glucose_min": 0.0,
      "damage_mean": 0.0,
      "damage_max": 0.0,
      "atp_generated_mean": 0.25842696629213485,
      "atp_generated_max": 2.0
    },
    {
      "t": 32,
      "n_cell": 300,
      "n_total": 4000,
      "n_match": 3787,
      "n_mismatch": 213,
      "n_cell_outside_morph": 0,
      "n_morph_without_cell": 213,
      "mean_match": 0.94675,
      "morphological_health": 0.33473897030518773,
      "atp_mean": 2.6933333333333334,
      "atp_min": 1.0,
      "atp_max": 4.0,
      "frac_atp_lt1": 0.0,
      "glucose_mean": 0.02666666666666667,
      "glucose_min": 0.0,
      "damage_mean": 0.0,
      "damage_max": 0.0,
      "atp_generated_mean": 0.02666666666666667,
      "atp_generated_max": 1.0
    },
    {
      "t": 33,
      "n_cell": 247,
      "n_total": 4000,
      "n_match": 3734,
      "n_mismatch": 266,
      "n_cell_outside_morph": 0,
      "n_morph_without_cell": 266,
      "mean_match": 0.9335,
      "morphological_health": 0.25251457226101115,
      "atp_mean": 2.0890688259109313,
      "atp_min": 1.0,
      "atp_max": 4.0,
      "frac_atp_lt1": 0.0,
      "glucose_mean": 0.0,
      "glucose_min": 0.0,
      "damage_mean": 0.0,
      "damage_max": 0.0,
      "atp_generated_mean": 0.0,
      "atp_generated_max": 0.0
    },
    {
      "t": 34,
      "n_cell": 177,
      "n_total": 4000,
      "n_match": 3664,
      "n_mismatch": 336,
      "n_cell_outside_morph": 0,
      "n_morph_without_cell": 336,
      "mean_match": 0.916,
      "morphological_health": 0.17294558247046243,
      "atp_mean": 1.5197740112994351,
      "atp_min": 1.0,
      "atp_max": 3.0,
      "frac_atp_lt1": 0.0,
      "glucose_mean": 0.0,
      "glucose_min": 0.0,
      "damage_mean": 0.0,
      "damage_max": 0.0,
      "atp_generated_mean": 0.0,
      "atp_generated_max": 0.0
    },
    {
      "t": 35,
      "n_cell": 84,
      "n_total": 4000,
      "n_match": 3571,
      "n_mismatch": 429,
      "n_cell_outside_morph": 0,
      "n_morph_without_cell": 429,
      "mean_match": 0.89275,
      "morphological_health": 0.10341824827265303,
      "atp_mean": 1.0952380952380953,
      "atp_min": 1.0,
      "atp_max": 2.0,
      "frac_atp_lt1": 0.0,
      "glucose_mean": 0.0,
      "glucose_min": 0.0,
      "damage_mean": 0.0,
      "damage_max": 0.0,
      "atp_generated_mean": 0.0,
      "atp_generated_max": 0.0
    },
    {
      "t": 36,
      "n_cell": 8,
      "n_total": 4000,
      "n_match": 3495,
      "n_mismatch": 505,
      "n_cell_outside_morph": 0,
      "n_morph_without_cell": 505,
      "mean_match": 0.87375,
      "morphological_health": 0.06725797308235267,
      "atp_mean": 1.0,
      "atp_min": 1.0,
      "atp_max": 1.0,
      "frac_atp_lt1": 0.0,
      "glucose_mean": 0.0,
      "glucose_min": 0.0,
      "damage_mean": 0.0,
      "damage_max": 0.0,
      "atp_generated_mean": 0.0,
      "atp_generated_max": 0.0
    },
    {
      "t": 37,
      "n_cell": 0,
      "n_total": 4000,
      "n_match": 3487,
      "n_mismatch": 513,
      "n_cell_outside_morph": 0,
      "n_morph_without_cell": 513,
      "mean_match": 0.87175,
      "morphological_health": 0.06424496856616034,
      "atp_mean": NaN,
      "atp_min": NaN,
      "atp_max": NaN,
      "frac_atp_lt1": NaN,
      "glucose_mean": NaN,
      "glucose_min": NaN,
      "damage_mean": NaN,
      "damage_max": NaN,
      "atp_generated_mean": NaN,
      "atp_generated_max": NaN
    },
    {
      "t": 38,
      "n_cell": 0,
      "n_total": 4000,
      "n_match": 3487,
      "n_mismatch": 513,
      "n_cell_outside_morph": 0,
      "n_morph_without_cell": 513,
      "mean_match": 0.87175,
      "morphological_health": 0.06424496856616034,
      "atp_mean": NaN,
      "atp_min": NaN,
      "atp_max": NaN,
      "frac_atp_lt1": NaN,
      "glucose_mean": NaN,
      "glucose_min": NaN,
      "damage_mean": NaN,
      "damage_max": NaN,
      "atp_generated_mean": NaN,
      "atp_generated_max": NaN
    },
    {
      "t": 39,
      "n_cell": 0,
      "n_total": 4000,
      "n_match": 3487,
      "n_mismatch": 513,
      "n_cell_outside_morph": 0,
      "n_morph_without_cell": 513,
      "mean_match": 0.87175,
      "morphological_health": 0.06424496856616034,
      "atp_mean": NaN,
      "atp_min": NaN,
      "atp_max": NaN,
      "frac_atp_lt1": NaN,
      "glucose_mean": NaN,
      "glucose_min": NaN,
      "damage_mean": NaN,
      "damage_max": NaN,
      "atp_generated_mean": NaN,
      "atp_generated_max": NaN
    },
    {
      "t": 40,
      "n_cell": 0,
      "n_total": 4000,
      "n_match": 3487,
      "n_mismatch": 513,
      "n_cell_outside_morph": 0,
      "n_morph_without_cell": 513,
      "mean_match": 0.87175,
      "morphological_health": 0.06424496856616034,
      "atp_mean": NaN,
      "atp_min": NaN,
      "atp_max": NaN,
      "frac_atp_lt1": NaN,
      "glucose_mean": NaN,
      "glucose_min": NaN,
      "damage_mean": NaN,
      "damage_max": NaN,
      "atp_generated_mean": NaN,
      "atp_generated_max": NaN
    },
    {
      "t": 41,
      "n_cell": 0,
      "n_total": 4000,
      "n_match": 3487,
      "n_mismatch": 513,
      "n_cell_outside_morph": 0,
      "n_morph_without_cell": 513,
      "mean_match": 0.87175,
      "morphological_health": 0.06424496856616034,
      "atp_mean": NaN,
      "atp_min": NaN,
      "atp_max": NaN,
      "frac_atp_lt1": NaN,
      "glucose_mean": NaN,
      "glucose_min": NaN,
      "damage_mean": NaN,
      "damage_max": NaN,
      "atp_generated_mean": NaN,
      "atp_generated_max": NaN
    },
    {
      "t": 42,
      "n_cell": 0,
      "n_total": 4000,
      "n_match": 3487,
      "n_mismatch": 513,
      "n_cell_outside_morph": 0,
      "n_morph_without_cell": 513,
      "mean_match": 0.87175,
      "morphological_health": 0.06424496856616034,
      "atp_mean": NaN,
      "atp_min": NaN,
      "atp_max": NaN,
      "frac_atp_lt1": NaN,
      "glucose_mean": NaN,
      "glucose_min": NaN,
      "damage_mean": NaN,
      "damage_max": NaN,
      "atp_generated_mean": NaN,
      "atp_generated_max": NaN
    },
    {
      "t": 43,
      "n_cell": 0,
      "n_total": 4000,
      "n_match": 3487,
      "n_mismatch": 513,
      "n_cell_outside_morph": 0,
      "n_morph_without_cell": 513,
      "mean_match": 0.87175,
      "morphological_health": 0.06424496856616034,
      "atp_mean": NaN,
      "atp_min": NaN,
      "atp_max": NaN,
      "frac_atp_lt1": NaN,
      "glucose_mean": NaN,
      "glucose_min": NaN,
      "damage_mean": NaN,
      "damage_max": NaN,
      "atp_generated_mean": NaN,
      "atp_generated_max": NaN
    },
    {
      "t": 44,
      "n_cell": 0,
      "n_total": 4000,
      "n_match": 3487,
      "n_mismatch": 513,
      "n_cell_outside_morph": 0,
      "n_morph_without_cell": 513,
      "mean_match": 0.87175,
      "morphological_health": 0.06424496856616034,
      "atp_mean": NaN,
      "atp_min": NaN,
      "atp_max": NaN,
      "frac_atp_lt1": NaN,
      "glucose_mean": NaN,
      "glucose_min": NaN,
      "damage_mean": NaN,
      "damage_max": NaN,
      "atp_generated_mean": NaN,
      "atp_generated_max": NaN
    },
    {
      "t": 45,
      "n_cell": 0,
      "n_total": 4000,
      "n_match": 3487,
      "n_mismatch": 513,
      "n_cell_outside_morph": 0,
      "n_morph_without_cell": 513,
      "mean_match": 0.87175,
      "morphological_health": 0.06424496856616034,
      "atp_mean": NaN,
      "atp_min": NaN,
      "atp_max": NaN,
      "frac_atp_lt1": NaN,
      "glucose_mean": NaN,
      "glucose_min": NaN,
      "damage_mean": NaN,
      "damage_max": NaN,
      "atp_generated_mean": NaN,
      "atp_generated_max": NaN
    },
    {
      "t": 46,
      "n_cell": 0,
      "n_total": 4000,
      "n_match": 3487,
      "n_mismatch": 513,
      "n_cell_outside_morph": 0,
      "n_morph_without_cell": 513,
      "mean_match": 0.87175,
      "morphological_health": 0.06424496856616034,
      "atp_mean": NaN,
      "atp_min": NaN,
      "atp_max": NaN,
      "frac_atp_lt1": NaN,
      "glucose_mean": NaN,
      "glucose_min": NaN,
      "damage_mean": NaN,
      "damage_max": NaN,
      "atp_generated_mean": NaN,
      "atp_generated_max": NaN
    },
    {
      "t": 47,
      "n_cell": 0,
      "n_total": 4000,
      "n_match": 3487,
      "n_mismatch": 513,
      "n_cell_outside_morph": 0,
      "n_morph_without_cell": 513,
      "mean_match": 0.87175,
      "morphological_health": 0.06424496856616034,
      "atp_mean": NaN,
      "atp_min": NaN,
      "atp_max": NaN,
      "frac_atp_lt1": NaN,
      "glucose_mean": NaN,
      "glucose_min": NaN,
      "damage_mean": NaN,
      "damage_max": NaN,
      "atp_generated_mean": NaN,
      "atp_generated_max": NaN
    },
    {
      "t": 48,
      "n_cell": 0,
      "n_total": 4000,
      "n_match": 3487,
      "n_mismatch": 513,
      "n_cell_outside_morph": 0,
      "n_morph_without_cell": 513,
      "mean_match": 0.87175,
      "morphological_health": 0.06424496856616034,
      "atp_mean": NaN,
      "atp_min": NaN,
      "atp_max": NaN,
      "frac_atp_lt1": NaN,
      "glucose_mean": NaN,
      "glucose_min": NaN,
      "damage_mean": NaN,
      "damage_max": NaN,
      "atp_generated_mean": NaN,
      "atp_generated_max": NaN
    },
    {
      "t": 49,
      "n_cell": 0,
      "n_total": 4000,
      "n_match": 3487,
      "n_mismatch": 513,
      "n_cell_outside_morph": 0,
      "n_morph_without_cell": 513,
      "mean_match": 0.87175,
      "morphological_health": 0.06424496856616034,
      "atp_mean": NaN,
      "atp_min": NaN,
      "atp_max": NaN,
      "frac_atp_lt1": NaN,
      "glucose_mean": NaN,
      "glucose_min": NaN,
      "damage_mean": NaN,
      "damage_max": NaN,
      "atp_generated_mean": NaN,
      "atp_generated_max": NaN
    },
    {
      "t": 50,
      "n_cell": 0,
      "n_total": 4000,
      "n_match": 3487,
      "n_mismatch": 513,
      "n_cell_outside_morph": 0,
      "n_morph_without_cell": 513,
      "mean_match": 0.87175,
      "morphological_health": 0.06424496856616034,
      "atp_mean": NaN,
      "atp_min": NaN,
      "atp_max": NaN,
      "frac_atp_lt1": NaN,
      "glucose_mean": NaN,
      "glucose_min": NaN,
      "damage_mean": NaN,
      "damage_max": NaN,
      "atp_generated_mean": NaN,
      "atp_generated_max": NaN
    },
    {
      "t": 51,
      "n_cell": 0,
      "n_total": 4000,
      "n_match": 3487,
      "n_mismatch": 513,
      "n_cell_outside_morph": 0,
      "n_morph_without_cell": 513,
      "mean_match": 0.87175,
      "morphological_health": 0.06424496856616034,
      "atp_mean": NaN,
      "atp_min": NaN,
      "atp_max": NaN,
      "frac_atp_lt1": NaN,
      "glucose_mean": NaN,
      "glucose_min": NaN,
      "damage_mean": NaN,
      "damage_max": NaN,
      "atp_generated_mean": NaN,
      "atp_generated_max": NaN
    },
    {
      "t": 52,
      "n_cell": 0,
      "n_total": 4000,
      "n_match": 3487,
      "n_mismatch": 513,
      "n_cell_outside_morph": 0,
      "n_morph_without_cell": 513,
      "mean_match": 0.87175,
      "morphological_health": 0.06424496856616034,
      "atp_mean": NaN,
      "atp_min": NaN,
      "atp_max": NaN,
      "frac_atp_lt1": NaN,
      "glucose_mean": NaN,
      "glucose_min": NaN,
      "damage_mean": NaN,
      "damage_max": NaN,
      "atp_generated_mean": NaN,
      "atp_generated_max": NaN
    },
    {
      "t": 53,
      "n_cell": 0,
      "n_total": 4000,
      "n_match": 3487,
      "n_mismatch": 513,
      "n_cell_outside_morph": 0,
      "n_morph_without_cell": 513,
      "mean_match": 0.87175,
      "morphological_health": 0.06424496856616034,
      "atp_mean": NaN,
      "atp_min": NaN,
      "atp_max": NaN,
      "frac_atp_lt1": NaN,
      "glucose_mean": NaN,
      "glucose_min": NaN,
      "damage_mean": NaN,
      "damage_max": NaN,
      "atp_generated_mean": NaN,
      "atp_generated_max": NaN
    },
    {
      "t": 54,
      "n_cell": 0,
      "n_total": 4000,
      "n_match": 3487,
      "n_mismatch": 513,
      "n_cell_outside_morph": 0,
      "n_morph_without_cell": 513,
      "mean_match": 0.87175,
      "morphological_health": 0.06424496856616034,
      "atp_mean": NaN,
      "atp_min": NaN,
      "atp_max": NaN,
      "frac_atp_lt1": NaN,
      "glucose_mean": NaN,
      "glucose_min": NaN,
      "damage_mean": NaN,
      "damage_max": NaN,
      "atp_generated_mean": NaN,
      "atp_generated_max": NaN
    },
    {
      "t": 55,
      "n_cell": 0,
      "n_total": 4000,
      "n_match": 3487,
      "n_mismatch": 513,
      "n_cell_outside_morph": 0,
      "n_morph_without_cell": 513,
      "mean_match": 0.87175,
      "morphological_health": 0.06424496856616034,
      "atp_mean": NaN,
      "atp_min": NaN,
      "atp_max": NaN,
      "frac_atp_lt1": NaN,
      "glucose_mean": NaN,
      "glucose_min": NaN,
      "damage_mean": NaN,
      "damage_max": NaN,
      "atp_generated_mean": NaN,
      "atp_generated_max": NaN
    },
    {
      "t": 56,
      "n_cell": 0,
      "n_total": 4000,
      "n_match": 3487,
      "n_mismatch": 513,
      "n_cell_outside_morph": 0,
      "n_morph_without_cell": 513,
      "mean_match": 0.87175,
      "morphological_health": 0.06424496856616034,
      "atp_mean": NaN,
      "atp_min": NaN,
      "atp_max": NaN,
      "frac_atp_lt1": NaN,
      "glucose_mean": NaN,
      "glucose_min": NaN,
      "damage_mean": NaN,
      "damage_max": NaN,
      "atp_generated_mean": NaN,
      "atp_generated_max": NaN
    },
    {
      "t": 57,
      "n_cell": 0,
      "n_total": 4000,
      "n_match": 3487,
      "n_mismatch": 513,
      "n_cell_outside_morph": 0,
      "n_morph_without_cell": 513,
      "mean_match": 0.87175,
      "morphological_health": 0.06424496856616034,
      "atp_mean": NaN,
      "atp_min": NaN,
      "atp_max": NaN,
      "frac_atp_lt1": NaN,
      "glucose_mean": NaN,
      "glucose_min": NaN,
      "damage_mean": NaN,
      "damage_max": NaN,
      "atp_generated_mean": NaN,
      "atp_generated_max": NaN
    },
    {
      "t": 58,
      "n_cell": 0,
      "n_total": 4000,
      "n_match": 3487,
      "n_mismatch": 513,
      "n_cell_outside_morph": 0,
      "n_morph_without_cell": 513,
      "mean_match": 0.87175,
      "morphological_health": 0.06424496856616034,
      "atp_mean": NaN,
      "atp_min": NaN,
      "atp_max": NaN,
      "frac_atp_lt1": NaN,
      "glucose_mean": NaN,
      "glucose_min": NaN,
      "damage_mean": NaN,
      "damage_max": NaN,
      "atp_generated_mean": NaN,
      "atp_generated_max": NaN
    },
    {
      "t": 59,
      "n_cell": 0,
      "n_total": 4000,
      "n_match": 3487,
      "n_mismatch": 513,
      "n_cell_outside_morph": 0,
      "n_morph_without_cell": 513,
      "mean_match": 0.87175,
      "morphological_health": 0.06424496856616034,
      "atp_mean": NaN,
      "atp_min": NaN,
      "atp_max": NaN,
      "frac_atp_lt1": NaN,
      "glucose_mean": NaN,
      "glucose_min": NaN,
      "damage_mean": NaN,
      "damage_max": NaN,
      "atp_generated_mean": NaN,
      "atp_generated_max": NaN
    },
    {
      "t": 60,
      "n_cell": 0,
      "n_total": 4000,
      "n_match": 3487,
      "n_mismatch": 513,
      "n_cell_outside_morph": 0,
      "n_morph_without_cell": 513,
      "mean_match": 0.87175,
      "morphological_health": 0.06424496856616034,
      "atp_mean": NaN,
      "atp_min": NaN,
      "atp_max": NaN,
      "frac_atp_lt1": NaN,
      "glucose_mean": NaN,
      "glucose_min": NaN,
      "damage_mean": NaN,
      "damage_max": NaN,
      "atp_generated_mean": NaN,
      "atp_generated_max": NaN
    },
    {
      "t": 61,
      "n_cell": 0,
      "n_total": 4000,
      "n_match": 3487,
      "n_mismatch": 513,
      "n_cell_outside_morph": 0,
      "n_morph_without_cell": 513,
      "mean_match": 0.87175,
      "morphological_health": 0.06424496856616034,
      "atp_mean": NaN,
      "atp_min": NaN,
      "atp_max": NaN,
      "frac_atp_lt1": NaN,
      "glucose_mean": NaN,
      "glucose_min": NaN,
      "damage_mean": NaN,
      "damage_max": NaN,
      "atp_generated_mean": NaN,
      "atp_generated_max": NaN
    },
    {
      "t": 62,
      "n_cell": 0,
      "n_total": 4000,
      "n_match": 3487,
      "n_mismatch": 513,
      "n_cell_outside_morph": 0,
      "n_morph_without_cell": 513,
      "mean_match": 0.87175,
      "morphological_health": 0.06424496856616034,
      "atp_mean": NaN,
      "atp_min": NaN,
      "atp_max": NaN,
      "frac_atp_lt1": NaN,
      "glucose_mean": NaN,
      "glucose_min": NaN,
      "damage_mean": NaN,
      "damage_max": NaN,
      "atp_generated_mean": NaN,
      "atp_generated_max": NaN
    },
    {
      "t": 63,
      "n_cell": 0,
      "n_total": 4000,
      "n_match": 3487,
      "n_mismatch": 513,
      "n_cell_outside_morph": 0,
      "n_morph_without_cell": 513,
      "mean_match": 0.87175,
      "morphological_health": 0.06424496856616034,
      "atp_mean": NaN,
      "atp_min": NaN,
      "atp_max": NaN,
      "frac_atp_lt1": NaN,
      "glucose_mean": NaN,
      "glucose_min": NaN,
      "damage_mean": NaN,
      "damage_max": NaN,
      "atp_generated_mean": NaN,
      "atp_generated_max": NaN
    },
    {
      "t": 64,
      "n_cell": 0,
      "n_total": 4000,
      "n_match": 3487,
      "n_mismatch": 513,
      "n_cell_outside_morph": 0,
      "n_morph_without_cell": 513,
      "mean_match": 0.87175,
      "morphological_health": 0.06424496856616034,
      "atp_mean": NaN,
      "atp_min": NaN,
      "atp_max": NaN,
      "frac_atp_lt1": NaN,
      "glucose_mean": NaN,
      "glucose_min": NaN,
      "damage_mean": NaN,
      "damage_max": NaN,
      "atp_generated_mean": NaN,
      "atp_generated_max": NaN
    },
    {
      "t": 65,
      "n_cell": 0,
      "n_total": 4000,
      "n_match": 3487,
      "n_mismatch": 513,
      "n_cell_outside_morph": 0,
      "n_morph_without_cell": 513,
      "mean_match": 0.87175,
      "morphological_health": 0.06424496856616034,
      "atp_mean": NaN,
      "atp_min": NaN,
      "atp_max": NaN,
      "frac_atp_lt1": NaN,
      "glucose_mean": NaN,
      "glucose_min": NaN,
      "damage_mean": NaN,
      "damage_max": NaN,
      "atp_generated_mean": NaN,
      "atp_generated_max": NaN
    },
    {
      "t": 66,
      "n_cell": 0,
      "n_total": 4000,
      "n_match": 3487,
      "n_mismatch": 513,
      "n_cell_outside_morph": 0,
      "n_morph_without_cell": 513,
      "mean_match": 0.87175,
      "morphological_health": 0.06424496856616034,
      "atp_mean": NaN,
      "atp_min": NaN,
      "atp_max": NaN,
      "frac_atp_lt1": NaN,
      "glucose_mean": NaN,
      "glucose_min": NaN,
      "damage_mean": NaN,
      "damage_max": NaN,
      "atp_generated_mean": NaN,
      "atp_generated_max": NaN
    },
    {
      "t": 67,
      "n_cell": 0,
      "n_total": 4000,
      "n_match": 3487,
      "n_mismatch": 513,
      "n_cell_outside_morph": 0,
      "n_morph_without_cell": 513,
      "mean_match": 0.87175,
      "morphological_health": 0.06424496856616034,
      "atp_mean": NaN,
      "atp_min": NaN,
      "atp_max": NaN,
      "frac_atp_lt1": NaN,
      "glucose_mean": NaN,
      "glucose_min": NaN,
      "damage_mean": NaN,
      "damage_max": NaN,
      "atp_generated_mean": NaN,
      "atp_generated_max": NaN
    },
    {
      "t": 68,
      "n_cell": 0,
      "n_total": 4000,
      "n_match": 3487,
      "n_mismatch": 513,
      "n_cell_outside_morph": 0,
      "n_morph_without_cell": 513,
      "mean_match": 0.87175,
      "morphological_health": 0.06424496856616034,
      "atp_mean": NaN,
      "atp_min": NaN,
      "atp_max": NaN,
      "frac_atp_lt1": NaN,
      "glucose_mean": NaN,
      "glucose_min": NaN,
      "damage_mean": NaN,
      "damage_max": NaN,
      "atp_generated_mean": NaN,
      "atp_generated_max": NaN
    },
    {
      "t": 69,
      "n_cell": 0,
      "n_total": 4000,
      "n_match": 3487,
      "n_mismatch": 513,
      "n_cell_outside_morph": 0,
      "n_morph_without_cell": 513,
      "mean_match": 0.87175,
      "morphological_health": 0.06424496856616034,
      "atp_mean": NaN,
      "atp_min": NaN,
      "atp_max": NaN,
      "frac_atp_lt1": NaN,
      "glucose_mean": NaN,
      "glucose_min": NaN,
      "damage_mean": NaN,
      "damage_max": NaN,
      "atp_generated_mean": NaN,
      "atp_generated_max": NaN
    },
    {
      "t": 70,
      "n_cell": 0,
      "n_total": 4000,
      "n_match": 3487,
      "n_mismatch": 513,
      "n_cell_outside_morph": 0,
      "n_morph_without_cell": 513,
      "mean_match": 0.87175,
      "morphological_health": 0.06424496856616034,
      "atp_mean": NaN,
      "atp_min": NaN,
      "atp_max": NaN,
      "frac_atp_lt1": NaN,
      "glucose_mean": NaN,
      "glucose_min": NaN,
      "damage_mean": NaN,
      "damage_max": NaN,
      "atp_generated_mean": NaN,
      "atp_generated_max": NaN
    },
    {
      "t": 71,
      "n_cell": 0,
      "n_total": 4000,
      "n_match": 3487,
      "n_mismatch": 513,
      "n_cell_outside_morph": 0,
      "n_morph_without_cell": 513,
      "mean_match": 0.87175,
      "morphological_health": 0.06424496856616034,
      "atp_mean": NaN,
      "atp_min": NaN,
      "atp_max": NaN,
      "frac_atp_lt1": NaN,
      "glucose_mean": NaN,
      "glucose_min": NaN,
      "damage_mean": NaN,
      "damage_max": NaN,
      "atp_generated_mean": NaN,
      "atp_generated_max": NaN
    },
    {
      "t": 72,
      "n_cell": 0,
      "n_total": 4000,
      "n_match": 3487,
      "n_mismatch": 513,
      "n_cell_outside_morph": 0,
      "n_morph_without_cell": 513,
      "mean_match": 0.87175,
      "morphological_health": 0.06424496856616034,
      "atp_mean": NaN,
      "atp_min": NaN,
      "atp_max": NaN,
      "frac_atp_lt1": NaN,
      "glucose_mean": NaN,
      "glucose_min": NaN,
      "damage_mean": NaN,
      "damage_max": NaN,
      "atp_generated_mean": NaN,
      "atp_generated_max": NaN
    },
    {
      "t": 73,
      "n_cell": 0,
      "n_total": 4000,
      "n_match": 3487,
      "n_mismatch": 513,
      "n_cell_outside_morph": 0,
      "n_morph_without_cell": 513,
      "mean_match": 0.87175,
      "morphological_health": 0.06424496856616034,
      "atp_mean": NaN,
      "atp_min": NaN,
      "atp_max": NaN,
      "frac_atp_lt1": NaN,
      "glucose_mean": NaN,
      "glucose_min": NaN,
      "damage_mean": NaN,
      "damage_max": NaN,
      "atp_generated_mean": NaN,
      "atp_generated_max": NaN
    },
    {
      "t": 74,
      "n_cell": 0,
      "n_total": 4000,
      "n_match": 3487,
      "n_mismatch": 513,
      "n_cell_outside_morph": 0,
      "n_morph_without_cell": 513,
      "mean_match": 0.87175,
      "morphological_health": 0.06424496856616034,
      "atp_mean": NaN,
      "atp_min": NaN,
      "atp_max": NaN,
      "frac_atp_lt1": NaN,
      "glucose_mean": NaN,
      "glucose_min": NaN,
      "damage_mean": NaN,
      "damage_max": NaN,
      "atp_generated_mean": NaN,
      "atp_generated_max": NaN
    },
    {
      "t": 75,
      "n_cell": 0,
      "n_total": 4000,
      "n_match": 3487,
      "n_mismatch": 513,
      "n_cell_outside_morph": 0,
      "n_morph_without_cell": 513,
      "mean_match": 0.87175,
      "morphological_health": 0.06424496856616034,
      "atp_mean": NaN,
      "atp_min": NaN,
      "atp_max": NaN,
      "frac_atp_lt1": NaN,
      "glucose_mean": NaN,
      "glucose_min": NaN,
      "damage_mean": NaN,
      "damage_max": NaN,
      "atp_generated_mean": NaN,
      "atp_generated_max": NaN
    },
    {
      "t": 76,
      "n_cell": 0,
      "n_total": 4000,
      "n_match": 3487,
      "n_mismatch": 513,
      "n_cell_outside_morph": 0,
      "n_morph_without_cell": 513,
      "mean_match": 0.87175,
      "morphological_health": 0.06424496856616034,
      "atp_mean": NaN,
      "atp_min": NaN,
      "atp_max": NaN,
      "frac_atp_lt1": NaN,
      "glucose_mean": NaN,
      "glucose_min": NaN,
      "damage_mean": NaN,
      "damage_max": NaN,
      "atp_generated_mean": NaN,
      "atp_generated_max": NaN
    },
    {
      "t": 77,
      "n_cell": 0,
      "n_total": 4000,
      "n_match": 3487,
      "n_mismatch": 513,
      "n_cell_outside_morph": 0,
      "n_morph_without_cell": 513,
      "mean_match": 0.87175,
      "morphological_health": 0.06424496856616034,
      "atp_mean": NaN,
      "atp_min": NaN,
      "atp_max": NaN,
      "frac_atp_lt1": NaN,
      "glucose_mean": NaN,
      "glucose_min": NaN,
      "damage_mean": NaN,
      "damage_max": NaN,
      "atp_generated_mean": NaN,
      "atp_generated_max": NaN
    },
    {
      "t": 78,
      "n_cell": 0,
      "n_total": 4000,
      "n_match": 3487,
      "n_mismatch": 513,
      "n_cell_outside_morph": 0,
      "n_morph_without_cell": 513,
      "mean_match": 0.87175,
      "morphological_health": 0.06424496856616034,
      "atp_mean": NaN,
      "atp_min": NaN,
      "atp_max": NaN,
      "frac_atp_lt1": NaN,
      "glucose_mean": NaN,
      "glucose_min": NaN,
      "damage_mean": NaN,
      "damage_max": NaN,
      "atp_generated_mean": NaN,
      "atp_generated_max": NaN
    },
    {
      "t": 79,
      "n_cell": 0,
      "n_total": 4000,
      "n_match": 3487,
      "n_mismatch": 513,
      "n_cell_outside_morph": 0,
      "n_morph_without_cell": 513,
      "mean_match": 0.87175,
      "morphological_health": 0.06424496856616034,
      "atp_mean": NaN,
      "atp_min": NaN,
      "atp_max": NaN,
      "frac_atp_lt1": NaN,
      "glucose_mean": NaN,
      "glucose_min": NaN,
      "damage_mean": NaN,
      "damage_max": NaN,
      "atp_generated_mean": NaN,
      "atp_generated_max": NaN
    },
    {
      "t": 80,
      "n_cell": 0,
      "n_total": 4000,
      "n_match": 3487,
      "n_mismatch": 513,
      "n_cell_outside_morph": 0,
      "n_morph_without_cell": 513,
      "mean_match": 0.87175,
      "morphological_health": 0.06424496856616034,
      "atp_mean": NaN,
      "atp_min": NaN,
      "atp_max": NaN,
      "frac_atp_lt1": NaN,
      "glucose_mean": NaN,
      "glucose_min": NaN,
      "damage_mean": NaN,
      "damage_max": NaN,
      "atp_generated_mean": NaN,
      "atp_generated_max": NaN
    },
    {
      "t": 81,
      "n_cell": 0,
      "n_total": 4000,
      "n_match": 3487,
      "n_mismatch": 513,
      "n_cell_outside_morph": 0,
      "n_morph_without_cell": 513,
      "mean_match": 0.87175,
      "morphological_health": 0.06424496856616034,
      "atp_mean": NaN,
      "atp_min": NaN,
      "atp_max": NaN,
      "frac_atp_lt1": NaN,
      "glucose_mean": NaN,
      "glucose_min": NaN,
      "damage_mean": NaN,
      "damage_max": NaN,
      "atp_generated_mean": NaN,
      "atp_generated_max": NaN
    },
    {
      "t": 82,
      "n_cell": 0,
      "n_total": 4000,
      "n_match": 3487,
      "n_mismatch": 513,
      "n_cell_outside_morph": 0,
      "n_morph_without_cell": 513,
      "mean_match": 0.87175,
      "morphological_health": 0.06424496856616034,
      "atp_mean": NaN,
      "atp_min": NaN,
      "atp_max": NaN,
      "frac_atp_lt1": NaN,
      "glucose_mean": NaN,
      "glucose_min": NaN,
      "damage_mean": NaN,
      "damage_max": NaN,
      "atp_generated_mean": NaN,
      "atp_generated_max": NaN
    },
    {
      "t": 83,
      "n_cell": 0,
      "n_total": 4000,
      "n_match": 3487,
      "n_mismatch": 513,
      "n_cell_outside_morph": 0,
      "n_morph_without_cell": 513,
      "mean_match": 0.87175,
      "morphological_health": 0.06424496856616034,
      "atp_mean": NaN,
      "atp_min": NaN,
      "atp_max": NaN,
      "frac_atp_lt1": NaN,
      "glucose_mean": NaN,
      "glucose_min": NaN,
      "damage_mean": NaN,
      "damage_max": NaN,
      "atp_generated_mean": NaN,
      "atp_generated_max": NaN
    },
    {
      "t": 84,
      "n_cell": 0,
      "n_total": 4000,
      "n_match": 3487,
      "n_mismatch": 513,
      "n_cell_outside_morph": 0,
      "n_morph_without_cell": 513,
      "mean_match": 0.87175,
      "morphological_health": 0.06424496856616034,
      "atp_mean": NaN,
      "atp_min": NaN,
      "atp_max": NaN,
      "frac_atp_lt1": NaN,
      "glucose_mean": NaN,
      "glucose_min": NaN,
      "damage_mean": NaN,
      "damage_max": NaN,
      "atp_generated_mean": NaN,
      "atp_generated_max": NaN
    },
    {
      "t": 85,
      "n_cell": 0,
      "n_total": 4000,
      "n_match": 3487,
      "n_mismatch": 513,
      "n_cell_outside_morph": 0,
      "n_morph_without_cell": 513,
      "mean_match": 0.87175,
      "morphological_health": 0.06424496856616034,
      "atp_mean": NaN,
      "atp_min": NaN,
      "atp_max": NaN,
      "frac_atp_lt1": NaN,
      "glucose_mean": NaN,
      "glucose_min": NaN,
      "damage_mean": NaN,
      "damage_max": NaN,
      "atp_generated_mean": NaN,
      "atp_generated_max": NaN
    },
    {
      "t": 86,
      "n_cell": 0,
      "n_total": 4000,
      "n_match": 3487,
      "n_mismatch": 513,
      "n_cell_outside_morph": 0,
      "n_morph_without_cell": 513,
      "mean_match": 0.87175,
      "morphological_health": 0.06424496856616034,
      "atp_mean": NaN,
      "atp_min": NaN,
      "atp_max": NaN,
      "frac_atp_lt1": NaN,
      "glucose_mean": NaN,
      "glucose_min": NaN,
      "damage_mean": NaN,
      "damage_max": NaN,
      "atp_generated_mean": NaN,
      "atp_generated_max": NaN
    },
    {
      "t": 87,
      "n_cell": 0,
      "n_total": 4000,
      "n_match": 3487,
      "n_mismatch": 513,
      "n_cell_outside_morph": 0,
      "n_morph_without_cell": 513,
      "mean_match": 0.87175,
      "morphological_health": 0.06424496856616034,
      "atp_mean": NaN,
      "atp_min": NaN,
      "atp_max": NaN,
      "frac_atp_lt1": NaN,
      "glucose_mean": NaN,
      "glucose_min": NaN,
      "damage_mean": NaN,
      "damage_max": NaN,
      "atp_generated_mean": NaN,
      "atp_generated_max": NaN
    },
    {
      "t": 88,
      "n_cell": 0,
      "n_total": 4000,
      "n_match": 3487,
      "n_mismatch": 513,
      "n_cell_outside_morph": 0,
      "n_morph_without_cell": 513,
      "mean_match": 0.87175,
      "morphological_health": 0.06424496856616034,
      "atp_mean": NaN,
      "atp_min": NaN,
      "atp_max": NaN,
      "frac_atp_lt1": NaN,
      "glucose_mean": NaN,
      "glucose_min": NaN,
      "damage_mean": NaN,
      "damage_max": NaN,
      "atp_generated_mean": NaN,
      "atp_generated_max": NaN
    },
    {
      "t": 89,
      "n_cell": 0,
      "n_total": 4000,
      "n_match": 3487,
      "n_mismatch": 513,
      "n_cell_outside_morph": 0,
      "n_morph_without_cell": 513,
      "mean_match": 0.87175,
      "morphological_health": 0.06424496856616034,
      "atp_mean": NaN,
      "atp_min": NaN,
      "atp_max": NaN,
      "frac_atp_lt1": NaN,
      "glucose_mean": NaN,
      "glucose_min": NaN,
      "damage_mean": NaN,
      "damage_max": NaN,
      "atp_generated_mean": NaN,
      "atp_generated_max": NaN
    },
    {
      "t": 90,
      "n_cell": 0,
      "n_total": 4000,
      "n_match": 3487,
      "n_mismatch": 513,
      "n_cell_outside_morph": 0,
      "n_morph_without_cell": 513,
      "mean_match": 0.87175,
      "morphological_health": 0.06424496856616034,
      "atp_mean": NaN,
      "atp_min": NaN,
      "atp_max": NaN,
      "frac_atp_lt1": NaN,
      "glucose_mean": NaN,
      "glucose_min": NaN,
      "damage_mean": NaN,
      "damage_max": NaN,
      "atp_generated_mean": NaN,
      "atp_generated_max": NaN
    },
    {
      "t": 91,
      "n_cell": 0,
      "n_total": 4000,
      "n_match": 3487,
      "n_mismatch": 513,
      "n_cell_outside_morph": 0,
      "n_morph_without_cell": 513,
      "mean_match": 0.87175,
      "morphological_health": 0.06424496856616034,
      "atp_mean": NaN,
      "atp_min": NaN,
      "atp_max": NaN,
      "frac_atp_lt1": NaN,
      "glucose_mean": NaN,
      "glucose_min": NaN,
      "damage_mean": NaN,
      "damage_max": NaN,
      "atp_generated_mean": NaN,
      "atp_generated_max": NaN
    },
    {
      "t": 92,
      "n_cell": 0,
      "n_total": 4000,
      "n_match": 3487,
      "n_mismatch": 513,
      "n_cell_outside_morph": 0,
      "n_morph_without_cell": 513,
      "mean_match": 0.87175,
      "morphological_health": 0.06424496856616034,
      "atp_mean": NaN,
      "atp_min": NaN,
      "atp_max": NaN,
      "frac_atp_lt1": NaN,
      "glucose_mean": NaN,
      "glucose_min": NaN,
      "damage_mean": NaN,
      "damage_max": NaN,
      "atp_generated_mean": NaN,
      "atp_generated_max": NaN
    },
    {
      "t": 93,
      "n_cell": 0,
      "n_total": 4000,
      "n_match": 3487,
      "n_mismatch": 513,
      "n_cell_outside_morph": 0,
      "n_morph_without_cell": 513,
      "mean_match": 0.87175,
      "morphological_health": 0.06424496856616034,
      "atp_mean": NaN,
      "atp_min": NaN,
      "atp_max": NaN,
      "frac_atp_lt1": NaN,
      "glucose_mean": NaN,
      "glucose_min": NaN,
      "damage_mean": NaN,
      "damage_max": NaN,
      "atp_generated_mean": NaN,
      "atp_generated_max": NaN
    },
    {
      "t": 94,
      "n_cell": 0,
      "n_total": 4000,
      "n_match": 3487,
      "n_mismatch": 513,
      "n_cell_outside_morph": 0,
      "n_morph_without_cell": 513,
      "mean_match": 0.87175,
      "morphological_health": 0.06424496856616034,
      "atp_mean": NaN,
      "atp_min": NaN,
      "atp_max": NaN,
      "frac_atp_lt1": NaN,
      "glucose_mean": NaN,
      "glucose_min": NaN,
      "damage_mean": NaN,
      "damage_max": NaN,
      "atp_generated_mean": NaN,
      "atp_generated_max": NaN
    },
    {
      "t": 95,
      "n_cell": 0,
      "n_total": 4000,
      "n_match": 3487,
      "n_mismatch": 513,
      "n_cell_outside_morph": 0,
      "n_morph_without_cell": 513,
      "mean_match": 0.87175,
      "morphological_health": 0.06424496856616034,
      "atp_mean": NaN,
      "atp_min": NaN,
      "atp_max": NaN,
      "frac_atp_lt1": NaN,
      "glucose_mean": NaN,
      "glucose_min": NaN,
      "damage_mean": NaN,
      "damage_max": NaN,
      "atp_generated_mean": NaN,
      "atp_generated_max": NaN
    },
    {
      "t": 96,
      "n_cell": 0,
      "n_total": 4000,
      "n_match": 3487,
      "n_mismatch": 513,
      "n_cell_outside_morph": 0,
      "n_morph_without_cell": 513,
      "mean_match": 0.87175,
      "morphological_health": 0.06424496856616034,
      "atp_mean": NaN,
      "atp_min": NaN,
      "atp_max": NaN,
      "frac_atp_lt1": NaN,
      "glucose_mean": NaN,
      "glucose_min": NaN,
      "damage_mean": NaN,
      "damage_max": NaN,
      "atp_generated_mean": NaN,
      "atp_generated_max": NaN
    },
    {
      "t": 97,
      "n_cell": 0,
      "n_total": 4000,
      "n_match": 3487,
      "n_mismatch": 513,
      "n_cell_outside_morph": 0,
      "n_morph_without_cell": 513,
      "mean_match": 0.87175,
      "morphological_health": 0.06424496856616034,
      "atp_mean": NaN,
      "atp_min": NaN,
      "atp_max": NaN,
      "frac_atp_lt1": NaN,
      "glucose_mean": NaN,
      "glucose_min": NaN,
      "damage_mean": NaN,
      "damage_max": NaN,
      "atp_generated_mean": NaN,
      "atp_generated_max": NaN
    },
    {
      "t": 98,
      "n_cell": 0,
      "n_total": 4000,
      "n_match": 3487,
      "n_mismatch": 513,
      "n_cell_outside_morph": 0,
      "n_morph_without_cell": 513,
      "mean_match": 0.87175,
      "morphological_health": 0.06424496856616034,
      "atp_mean": NaN,
      "atp_min": NaN,
      "atp_max": NaN,
      "frac_atp_lt1": NaN,
      "glucose_mean": NaN,
      "glucose_min": NaN,
      "damage_mean": NaN,
      "damage_max": NaN,
      "atp_generated_mean": NaN,
      "atp_generated_max": NaN
    },
    {
      "t": 99,
      "n_cell": 0,
      "n_total": 4000,
      "n_match": 3487,
      "n_mismatch": 513,
      "n_cell_outside_morph": 0,
      "n_morph_without_cell": 513,
      "mean_match": 0.87175,
      "morphological_health": 0.06424496856616034,
      "atp_mean": NaN,
      "atp_min": NaN,
      "atp_max": NaN,
      "frac_atp_lt1": NaN,
      "glucose_mean": NaN,
      "glucose_min": NaN,
      "damage_mean": NaN,
      "damage_max": NaN,
      "atp_generated_mean": NaN,
      "atp_generated_max": NaN
    },
    {
      "t": 100,
      "n_cell": 0,
      "n_total": 4000,
      "n_match": 3487,
      "n_mismatch": 513,
      "n_cell_outside_morph": 0,
      "n_morph_without_cell": 513,
      "mean_match": 0.87175,
      "morphological_health": 0.06424496856616034,
      "atp_mean": NaN,
      "atp_min": NaN,
      "atp_max": NaN,
      "frac_atp_lt1": NaN,
      "glucose_mean": NaN,
      "glucose_min": NaN,
      "damage_mean": NaN,
      "damage_max": NaN,
      "atp_generated_mean": NaN,
      "atp_generated_max": NaN
    },
    {
      "t": 101,
      "n_cell": 0,
      "n_total": 4000,
      "n_match": 3487,
      "n_mismatch": 513,
      "n_cell_outside_morph": 0,
      "n_morph_without_cell": 513,
      "mean_match": 0.87175,
      "morphological_health": 0.06424496856616034,
      "atp_mean": NaN,
      "atp_min": NaN,
      "atp_max": NaN,
      "frac_atp_lt1": NaN,
      "glucose_mean": NaN,
      "glucose_min": NaN,
      "damage_mean": NaN,
      "damage_max": NaN,
      "atp_generated_mean": NaN,
      "atp_generated_max": NaN
    },
    {
      "t": 102,
      "n_cell": 0,
      "n_total": 4000,
      "n_match": 3487,
      "n_mismatch": 513,
      "n_cell_outside_morph": 0,
      "n_morph_without_cell": 513,
      "mean_match": 0.87175,
      "morphological_health": 0.06424496856616034,
      "atp_mean": NaN,
      "atp_min": NaN,
      "atp_max": NaN,
      "frac_atp_lt1": NaN,
      "glucose_mean": NaN,
      "glucose_min": NaN,
      "damage_mean": NaN,
      "damage_max": NaN,
      "atp_generated_mean": NaN,
      "atp_generated_max": NaN
    },
    {
      "t": 103,
      "n_cell": 0,
      "n_total": 4000,
      "n_match": 3487,
      "n_mismatch": 513,
      "n_cell_outside_morph": 0,
      "n_morph_without_cell": 513,
      "mean_match": 0.87175,
      "morphological_health": 0.06424496856616034,
      "atp_mean": NaN,
      "atp_min": NaN,
      "atp_max": NaN,
      "frac_atp_lt1": NaN,
      "glucose_mean": NaN,
      "glucose_min": NaN,
      "damage_mean": NaN,
      "damage_max": NaN,
      "atp_generated_mean": NaN,
      "atp_generated_max": NaN
    },
    {
      "t": 104,
      "n_cell": 0,
      "n_total": 4000,
      "n_match": 3487,
      "n_mismatch": 513,
      "n_cell_outside_morph": 0,
      "n_morph_without_cell": 513,
      "mean_match": 0.87175,
      "morphological_health": 0.06424496856616034,
      "atp_mean": NaN,
      "atp_min": NaN,
      "atp_max": NaN,
      "frac_atp_lt1": NaN,
      "glucose_mean": NaN,
      "glucose_min": NaN,
      "damage_mean": NaN,
      "damage_max": NaN,
      "atp_generated_mean": NaN,
      "atp_generated_max": NaN
    },
    {
      "t": 105,
      "n_cell": 0,
      "n_total": 4000,
      "n_match": 3487,
      "n_mismatch": 513,
      "n_cell_outside_morph": 0,
      "n_morph_without_cell": 513,
      "mean_match": 0.87175,
      "morphological_health": 0.06424496856616034,
      "atp_mean": NaN,
      "atp_min": NaN,
      "atp_max": NaN,
      "frac_atp_lt1": NaN,
      "glucose_mean": NaN,
      "glucose_min": NaN,
      "damage_mean": NaN,
      "damage_max": NaN,
      "atp_generated_mean": NaN,
      "atp_generated_max": NaN
    },
    {
      "t": 106,
      "n_cell": 0,
      "n_total": 4000,
      "n_match": 3487,
      "n_mismatch": 513,
      "n_cell_outside_morph": 0,
      "n_morph_without_cell": 513,
      "mean_match": 0.87175,
      "morphological_health": 0.06424496856616034,
      "atp_mean": NaN,
      "atp_min": NaN,
      "atp_max": NaN,
      "frac_atp_lt1": NaN,
      "glucose_mean": NaN,
      "glucose_min": NaN,
      "damage_mean": NaN,
      "damage_max": NaN,
      "atp_generated_mean": NaN,
      "atp_generated_max": NaN
    },
    {
      "t": 107,
      "n_cell": 0,
      "n_total": 4000,
      "n_match": 3487,
      "n_mismatch": 513,
      "n_cell_outside_morph": 0,
      "n_morph_without_cell": 513,
      "mean_match": 0.87175,
      "morphological_health": 0.06424496856616034,
      "atp_mean": NaN,
      "atp_min": NaN,
      "atp_max": NaN,
      "frac_atp_lt1": NaN,
      "glucose_mean": NaN,
      "glucose_min": NaN,
      "damage_mean": NaN,
      "damage_max": NaN,
      "atp_generated_mean": NaN,
      "atp_generated_max": NaN
    },
    {
      "t": 108,
      "n_cell": 0,
      "n_total": 4000,
      "n_match": 3487,
      "n_mismatch": 513,
      "n_cell_outside_morph": 0,
      "n_morph_without_cell": 513,
      "mean_match": 0.87175,
      "morphological_health": 0.06424496856616034,
      "atp_mean": NaN,
      "atp_min": NaN,
      "atp_max": NaN,
      "frac_atp_lt1": NaN,
      "glucose_mean": NaN,
      "glucose_min": NaN,
      "damage_mean": NaN,
      "damage_max": NaN,
      "atp_generated_mean": NaN,
      "atp_generated_max": NaN
    },
    {
      "t": 109,
      "n_cell": 0,
      "n_total": 4000,
      "n_match": 3487,
      "n_mismatch": 513,
      "n_cell_outside_morph": 0,
      "n_morph_without_cell": 513,
      "mean_match": 0.87175,
      "morphological_health": 0.06424496856616034,
      "atp_mean": NaN,
      "atp_min": NaN,
      "atp_max": NaN,
      "frac_atp_lt1": NaN,
      "glucose_mean": NaN,
      "glucose_min": NaN,
      "damage_mean": NaN,
      "damage_max": NaN,
      "atp_generated_mean": NaN,
      "atp_generated_max": NaN
    },
    {
      "t": 110,
      "n_cell": 0,
      "n_total": 4000,
      "n_match": 3487,
      "n_mismatch": 513,
      "n_cell_outside_morph": 0,
      "n_morph_without_cell": 513,
      "mean_match": 0.87175,
      "morphological_health": 0.06424496856616034,
      "atp_mean": NaN,
      "atp_min": NaN,
      "atp_max": NaN,
      "frac_atp_lt1": NaN,
      "glucose_mean": NaN,
      "glucose_min": NaN,
      "damage_mean": NaN,
      "damage_max": NaN,
      "atp_generated_mean": NaN,
      "atp_generated_max": NaN
    },
    {
      "t": 111,
      "n_cell": 0,
      "n_total": 4000,
      "n_match": 3487,
      "n_mismatch": 513,
      "n_cell_outside_morph": 0,
      "n_morph_without_cell": 513,
      "mean_match": 0.87175,
      "morphological_health": 0.06424496856616034,
      "atp_mean": NaN,
      "atp_min": NaN,
      "atp_max": NaN,
      "frac_atp_lt1": NaN,
      "glucose_mean": NaN,
      "glucose_min": NaN,
      "damage_mean": NaN,
      "damage_max": NaN,
      "atp_generated_mean": NaN,
      "atp_generated_max": NaN
    },
    {
      "t": 112,
      "n_cell": 0,
      "n_total": 4000,
      "n_match": 3487,
      "n_mismatch": 513,
      "n_cell_outside_morph": 0,
      "n_morph_without_cell": 513,
      "mean_match": 0.87175,
      "morphological_health": 0.06424496856616034,
      "atp_mean": NaN,
      "atp_min": NaN,
      "atp_max": NaN,
      "frac_atp_lt1": NaN,
      "glucose_mean": NaN,
      "glucose_min": NaN,
      "damage_mean": NaN,
      "damage_max": NaN,
      "atp_generated_mean": NaN,
      "atp_generated_max": NaN
    },
    {
      "t": 113,
      "n_cell": 0,
      "n_total": 4000,
      "n_match": 3487,
      "n_mismatch": 513,
      "n_cell_outside_morph": 0,
      "n_morph_without_cell": 513,
      "mean_match": 0.87175,
      "morphological_health": 0.06424496856616034,
      "atp_mean": NaN,
      "atp_min": NaN,
      "atp_max": NaN,
      "frac_atp_lt1": NaN,
      "glucose_mean": NaN,
      "glucose_min": NaN,
      "damage_mean": NaN,
      "damage_max": NaN,
      "atp_generated_mean": NaN,
      "atp_generated_max": NaN
    },
    {
      "t": 114,
      "n_cell": 0,
      "n_total": 4000,
      "n_match": 3487,
      "n_mismatch": 513,
      "n_cell_outside_morph": 0,
      "n_morph_without_cell": 513,
      "mean_match": 0.87175,
      "morphological_health": 0.06424496856616034,
      "atp_mean": NaN,
      "atp_min": NaN,
      "atp_max": NaN,
      "frac_atp_lt1": NaN,
      "glucose_mean": NaN,
      "glucose_min": NaN,
      "damage_mean": NaN,
      "damage_max": NaN,
      "atp_generated_mean": NaN,
      "atp_generated_max": NaN
    },
    {
      "t": 115,
      "n_cell": 0,
      "n_total": 4000,
      "n_match": 3487,
      "n_mismatch": 513,
      "n_cell_outside_morph": 0,
      "n_morph_without_cell": 513,
      "mean_match": 0.87175,
      "morphological_health": 0.06424496856616034,
      "atp_mean": NaN,
      "atp_min": NaN,
      "atp_max": NaN,
      "frac_atp_lt1": NaN,
      "glucose_mean": NaN,
      "glucose_min": NaN,
      "damage_mean": NaN,
      "damage_max": NaN,
      "atp_generated_mean": NaN,
      "atp_generated_max": NaN
    },
    {
      "t": 116,
      "n_cell": 0,
      "n_total": 4000,
      "n_match": 3487,
      "n_mismatch": 513,
      "n_cell_outside_morph": 0,
      "n_morph_without_cell": 513,
      "mean_match": 0.87175,
      "morphological_health": 0.06424496856616034,
      "atp_mean": NaN,
      "atp_min": NaN,
      "atp_max": NaN,
      "frac_atp_lt1": NaN,
      "glucose_mean": NaN,
      "glucose_min": NaN,
      "damage_mean": NaN,
      "damage_max": NaN,
      "atp_generated_mean": NaN,
      "atp_generated_max": NaN
    },
    {
      "t": 117,
      "n_cell": 0,
      "n_total": 4000,
      "n_match": 3487,
      "n_mismatch": 513,
      "n_cell_outside_morph": 0,
      "n_morph_without_cell": 513,
      "mean_match": 0.87175,
      "morphological_health": 0.06424496856616034,
      "atp_mean": NaN,
      "atp_min": NaN,
      "atp_max": NaN,
      "frac_atp_lt1": NaN,
      "glucose_mean": NaN,
      "glucose_min": NaN,
      "damage_mean": NaN,
      "damage_max": NaN,
      "atp_generated_mean": NaN,
      "atp_generated_max": NaN
    },
    {
      "t": 118,
      "n_cell": 0,
      "n_total": 4000,
      "n_match": 3487,
      "n_mismatch": 513,
      "n_cell_outside_morph": 0,
      "n_morph_without_cell": 513,
      "mean_match": 0.87175,
      "morphological_health": 0.06424496856616034,
      "atp_mean": NaN,
      "atp_min": NaN,
      "atp_max": NaN,
      "frac_atp_lt1": NaN,
      "glucose_mean": NaN,
      "glucose_min": NaN,
      "damage_mean": NaN,
      "damage_max": NaN,
      "atp_generated_mean": NaN,
      "atp_generated_max": NaN
    },
    {
      "t": 119,
      "n_cell": 0,
      "n_total": 4000,
      "n_match": 3487,
      "n_mismatch": 513,
      "n_cell_outside_morph": 0,
      "n_morph_without_cell": 513,
      "mean_match": 0.87175,
      "morphological_health": 0.06424496856616034,
      "atp_mean": NaN,
      "atp_min": NaN,
      "atp_max": NaN,
      "frac_atp_lt1": NaN,
      "glucose_mean": NaN,
      "glucose_min": NaN,
      "damage_mean": NaN,
      "damage_max": NaN,
      "atp_generated_mean": NaN,
      "atp_generated_max": NaN
    },
    {
      "t": 120,
      "n_cell": 0,
      "n_total": 4000,
      "n_match": 3487,
      "n_mismatch": 513,
      "n_cell_outside_morph": 0,
      "n_morph_without_cell": 513,
      "mean_match": 0.87175,
      "morphological_health": 0.06424496856616034,
      "atp_mean": NaN,
      "atp_min": NaN,
      "atp_max": NaN,
      "frac_atp_lt1": NaN,
      "glucose_mean": NaN,
      "glucose_min": NaN,
      "damage_mean": NaN,
      "damage_max": NaN,
      "atp_generated_mean": NaN,
      "atp_generated_max": NaN
    },
    {
      "t": 121,
      "n_cell": 0,
      "n_total": 4000,
      "n_match": 3487,
      "n_mismatch": 513,
      "n_cell_outside_morph": 0,
      "n_morph_without_cell": 513,
      "mean_match": 0.87175,
      "morphological_health": 0.06424496856616034,
      "atp_mean": NaN,
      "atp_min": NaN,
      "atp_max": NaN,
      "frac_atp_lt1": NaN,
      "glucose_mean": NaN,
      "glucose_min": NaN,
      "damage_mean": NaN,
      "damage_max": NaN,
      "atp_generated_mean": NaN,
      "atp_generated_max": NaN
    },
    {
      "t": 122,
      "n_cell": 0,
      "n_total": 4000,
      "n_match": 3487,
      "n_mismatch": 513,
      "n_cell_outside_morph": 0,
      "n_morph_without_cell": 513,
      "mean_match": 0.87175,
      "morphological_health": 0.06424496856616034,
      "atp_mean": NaN,
      "atp_min": NaN,
      "atp_max": NaN,
      "frac_atp_lt1": NaN,
      "glucose_mean": NaN,
      "glucose_min": NaN,
      "damage_mean": NaN,
      "damage_max": NaN,
      "atp_generated_mean": NaN,
      "atp_generated_max": NaN
    },
    {
      "t": 123,
      "n_cell": 0,
      "n_total": 4000,
      "n_match": 3487,
      "n_mismatch": 513,
      "n_cell_outside_morph": 0,
      "n_morph_without_cell": 513,
      "mean_match": 0.87175,
      "morphological_health": 0.06424496856616034,
      "atp_mean": NaN,
      "atp_min": NaN,
      "atp_max": NaN,
      "frac_atp_lt1": NaN,
      "glucose_mean": NaN,
      "glucose_min": NaN,
      "damage_mean": NaN,
      "damage_max": NaN,
      "atp_generated_mean": NaN,
      "atp_generated_max": NaN
    },
    {
      "t": 124,
      "n_cell": 0,
      "n_total": 4000,
      "n_match": 3487,
      "n_mismatch": 513,
      "n_cell_outside_morph": 0,
      "n_morph_without_cell": 513,
      "mean_match": 0.87175,
      "morphological_health": 0.06424496856616034,
      "atp_mean": NaN,
      "atp_min": NaN,
      "atp_max": NaN,
      "frac_atp_lt1": NaN,
      "glucose_mean": NaN,
      "glucose_min": NaN,
      "damage_mean": NaN,
      "damage_max": NaN,
      "atp_generated_mean": NaN,
      "atp_generated_max": NaN
    },
    {
      "t": 125,
      "n_cell": 0,
      "n_total": 4000,
      "n_match": 3487,
      "n_mismatch": 513,
      "n_cell_outside_morph": 0,
      "n_morph_without_cell": 513,
      "mean_match": 0.87175,
      "morphological_health": 0.06424496856616034,
      "atp_mean": NaN,
      "atp_min": NaN,
      "atp_max": NaN,
      "frac_atp_lt1": NaN,
      "glucose_mean": NaN,
      "glucose_min": NaN,
      "damage_mean": NaN,
      "damage_max": NaN,
      "atp_generated_mean": NaN,
      "atp_generated_max": NaN
    },
    {
      "t": 126,
      "n_cell": 0,
      "n_total": 4000,
      "n_match": 3487,
      "n_mismatch": 513,
      "n_cell_outside_morph": 0,
      "n_morph_without_cell": 513,
      "mean_match": 0.87175,
      "morphological_health": 0.06424496856616034,
      "atp_mean": NaN,
      "atp_min": NaN,
      "atp_max": NaN,
      "frac_atp_lt1": NaN,
      "glucose_mean": NaN,
      "glucose_min": NaN,
      "damage_mean": NaN,
      "damage_max": NaN,
      "atp_generated_mean": NaN,
      "atp_generated_max": NaN
    },
    {
      "t": 127,
      "n_cell": 0,
      "n_total": 4000,
      "n_match": 3487,
      "n_mismatch": 513,
      "n_cell_outside_morph": 0,
      "n_morph_without_cell": 513,
      "mean_match": 0.87175,
      "morphological_health": 0.06424496856616034,
      "atp_mean": NaN,
      "atp_min": NaN,
      "atp_max": NaN,
      "frac_atp_lt1": NaN,
      "glucose_mean": NaN,
      "glucose_min": NaN,
      "damage_mean": NaN,
      "damage_max": NaN,
      "atp_generated_mean": NaN,
      "atp_generated_max": NaN
    },
    {
      "t": 128,
      "n_cell": 0,
      "n_total": 4000,
      "n_match": 3487,
      "n_mismatch": 513,
      "n_cell_outside_morph": 0,
      "n_morph_without_cell": 513,
      "mean_match": 0.87175,
      "morphological_health": 0.06424496856616034,
      "atp_mean": NaN,
      "atp_min": NaN,
      "atp_max": NaN,
      "frac_atp_lt1": NaN,
      "glucose_mean": NaN,
      "glucose_min": NaN,
      "damage_mean": NaN,
      "damage_max": NaN,
      "atp_generated_mean": NaN,
      "atp_generated_max": NaN
    },
    {
      "t": 129,
      "n_cell": 0,
      "n_total": 4000,
      "n_match": 3487,
      "n_mismatch": 513,
      "n_cell_outside_morph": 0,
      "n_morph_without_cell": 513,
      "mean_match": 0.87175,
      "morphological_health": 0.06424496856616034,
      "atp_mean": NaN,
      "atp_min": NaN,
      "atp_max": NaN,
      "frac_atp_lt1": NaN,
      "glucose_mean": NaN,
      "glucose_min": NaN,
      "damage_mean": NaN,
      "damage_max": NaN,
      "atp_generated_mean": NaN,
      "atp_generated_max": NaN
    },
    {
      "t": 130,
      "n_cell": 0,
      "n_total": 4000,
      "n_match": 3487,
      "n_mismatch": 513,
      "n_cell_outside_morph": 0,
      "n_morph_without_cell": 513,
      "mean_match": 0.87175,
      "morphological_health": 0.06424496856616034,
      "atp_mean": NaN,
      "atp_min": NaN,
      "atp_max": NaN,
      "frac_atp_lt1": NaN,
      "glucose_mean": NaN,
      "glucose_min": NaN,
      "damage_mean": NaN,
      "damage_max": NaN,
      "atp_generated_mean": NaN,
      "atp_generated_max": NaN
    },
    {
      "t": 131,
      "n_cell": 0,
      "n_total": 4000,
      "n_match": 3487,
      "n_mismatch": 513,
      "n_cell_outside_morph": 0,
      "n_morph_without_cell": 513,
      "mean_match": 0.87175,
      "morphological_health": 0.06424496856616034,
      "atp_mean": NaN,
      "atp_min": NaN,
      "atp_max": NaN,
      "frac_atp_lt1": NaN,
      "glucose_mean": NaN,
      "glucose_min": NaN,
      "damage_mean": NaN,
      "damage_max": NaN,
      "atp_generated_mean": NaN,
      "atp_generated_max": NaN
    },
    {
      "t": 132,
      "n_cell": 0,
      "n_total": 4000,
      "n_match": 3487,
      "n_mismatch": 513,
      "n_cell_outside_morph": 0,
      "n_morph_without_cell": 513,
      "mean_match": 0.87175,
      "morphological_health": 0.06424496856616034,
      "atp_mean": NaN,
      "atp_min": NaN,
      "atp_max": NaN,
      "frac_atp_lt1": NaN,
      "glucose_mean": NaN,
      "glucose_min": NaN,
      "damage_mean": NaN,
      "damage_max": NaN,
      "atp_generated_mean": NaN,
      "atp_generated_max": NaN
    },
    {
      "t": 133,
      "n_cell": 0,
      "n_total": 4000,
      "n_match": 3487,
      "n_mismatch": 513,
      "n_cell_outside_morph": 0,
      "n_morph_without_cell": 513,
      "mean_match": 0.87175,
      "morphological_health": 0.06424496856616034,
      "atp_mean": NaN,
      "atp_min": NaN,
      "atp_max": NaN,
      "frac_atp_lt1": NaN,
      "glucose_mean": NaN,
      "glucose_min": NaN,
      "damage_mean": NaN,
      "damage_max": NaN,
      "atp_generated_mean": NaN,
      "atp_generated_max": NaN
    },
    {
      "t": 134,
      "n_cell": 0,
      "n_total": 4000,
      "n_match": 3487,
      "n_mismatch": 513,
      "n_cell_outside_morph": 0,
      "n_morph_without_cell": 513,
      "mean_match": 0.87175,
      "morphological_health": 0.06424496856616034,
      "atp_mean": NaN,
      "atp_min": NaN,
      "atp_max": NaN,
      "frac_atp_lt1": NaN,
      "glucose_mean": NaN,
      "glucose_min": NaN,
      "damage_mean": NaN,
      "damage_max": NaN,
      "atp_generated_mean": NaN,
      "atp_generated_max": NaN
    },
    {
      "t": 135,
      "n_cell": 0,
      "n_total": 4000,
      "n_match": 3487,
      "n_mismatch": 513,
      "n_cell_outside_morph": 0,
      "n_morph_without_cell": 513,
      "mean_match": 0.87175,
      "morphological_health": 0.06424496856616034,
      "atp_mean": NaN,
      "atp_min": NaN,
      "atp_max": NaN,
      "frac_atp_lt1": NaN,
      "glucose_mean": NaN,
      "glucose_min": NaN,
      "damage_mean": NaN,
      "damage_max": NaN,
      "atp_generated_mean": NaN,
      "atp_generated_max": NaN
    },
    {
      "t": 136,
      "n_cell": 0,
      "n_total": 4000,
      "n_match": 3487,
      "n_mismatch": 513,
      "n_cell_outside_morph": 0,
      "n_morph_without_cell": 513,
      "mean_match": 0.87175,
      "morphological_health": 0.06424496856616034,
      "atp_mean": NaN,
      "atp_min": NaN,
      "atp_max": NaN,
      "frac_atp_lt1": NaN,
      "glucose_mean": NaN,
      "glucose_min": NaN,
      "damage_mean": NaN,
      "damage_max": NaN,
      "atp_generated_mean": NaN,
      "atp_generated_max": NaN
    },
    {
      "t": 137,
      "n_cell": 0,
      "n_total": 4000,
      "n_match": 3487,
      "n_mismatch": 513,
      "n_cell_outside_morph": 0,
      "n_morph_without_cell": 513,
      "mean_match": 0.87175,
      "morphological_health": 0.06424496856616034,
      "atp_mean": NaN,
      "atp_min": NaN,
      "atp_max": NaN,
      "frac_atp_lt1": NaN,
      "glucose_mean": NaN,
      "glucose_min": NaN,
      "damage_mean": NaN,
      "damage_max": NaN,
      "atp_generated_mean": NaN,
      "atp_generated_max": NaN
    },
    {
      "t": 138,
      "n_cell": 0,
      "n_total": 4000,
      "n_match": 3487,
      "n_mismatch": 513,
      "n_cell_outside_morph": 0,
      "n_morph_without_cell": 513,
      "mean_match": 0.87175,
      "morphological_health": 0.06424496856616034,
      "atp_mean": NaN,
      "atp_min": NaN,
      "atp_max": NaN,
      "frac_atp_lt1": NaN,
      "glucose_mean": NaN,
      "glucose_min": NaN,
      "damage_mean": NaN,
      "damage_max": NaN,
      "atp_generated_mean": NaN,
      "atp_generated_max": NaN
    },
    {
      "t": 139,
      "n_cell": 0,
      "n_total": 4000,
      "n_match": 3487,
      "n_mismatch": 513,
      "n_cell_outside_morph": 0,
      "n_morph_without_cell": 513,
      "mean_match": 0.87175,
      "morphological_health": 0.06424496856616034,
      "atp_mean": NaN,
      "atp_min": NaN,
      "atp_max": NaN,
      "frac_atp_lt1": NaN,
      "glucose_mean": NaN,
      "glucose_min": NaN,
      "damage_mean": NaN,
      "damage_max": NaN,
      "atp_generated_mean": NaN,
      "atp_generated_max": NaN
    },
    {
      "t": 140,
      "n_cell": 0,
      "n_total": 4000,
      "n_match": 3487,
      "n_mismatch": 513,
      "n_cell_outside_morph": 0,
      "n_morph_without_cell": 513,
      "mean_match": 0.87175,
      "morphological_health": 0.06424496856616034,
      "atp_mean": NaN,
      "atp_min": NaN,
      "atp_max": NaN,
      "frac_atp_lt1": NaN,
      "glucose_mean": NaN,
      "glucose_min": NaN,
      "damage_mean": NaN,
      "damage_max": NaN,
      "atp_generated_mean": NaN,
      "atp_generated_max": NaN
    }
  ]
}